{
  "generated_at": "2026-03-12T19:43:23.325884+00:00",
  "prices": {
    "brent": {
      "name": "Brent Oil",
      "price": 97.35,
      "change": 5.84,
      "formatted_price": "$97.35",
      "formatted_change": "+5.84%",
      "updated_at": "2026-03-12T19:43:23.065977+00:00"
    },
    "gas": {
      "name": "Natural Gas",
      "price": 3.227,
      "change": 0.56,
      "formatted_price": "$3.227",
      "formatted_change": "+0.56%",
      "updated_at": "2026-03-12T19:43:23.151997+00:00"
    },
    "gold": {
      "name": "Gold",
      "price": 5102.3,
      "change": -1.26,
      "formatted_price": "$5102",
      "formatted_change": "-1.26%",
      "updated_at": "2026-03-12T19:43:23.219933+00:00"
    },
    "bitcoin": {
      "name": "Bitcoin",
      "price": 70328.195,
      "change": 0.18,
      "formatted_price": "$70,328",
      "formatted_change": "+0.18%",
      "updated_at": "2026-03-12T19:43:23.325866+00:00"
    }
  }
}