{
  "generated_at": "2026-03-17T04:48:35.364767+00:00",
  "prices": {
    "brent": {
      "name": "Brent Oil",
      "price": 102.81,
      "change": 2.59,
      "formatted_price": "$102.81",
      "formatted_change": "+2.59%",
      "updated_at": "2026-03-17T04:48:35.030865+00:00"
    },
    "gas": {
      "name": "Natural Gas",
      "price": 3.018,
      "change": -0.17,
      "formatted_price": "$3.018",
      "formatted_change": "-0.17%",
      "updated_at": "2026-03-17T04:48:35.109784+00:00"
    },
    "gold": {
      "name": "Gold",
      "price": 5038.7,
      "change": 0.73,
      "formatted_price": "$5039",
      "formatted_change": "+0.73%",
      "updated_at": "2026-03-17T04:48:35.206876+00:00"
    },
    "bitcoin": {
      "name": "Bitcoin",
      "price": 74083.36,
      "change": -1.05,
      "formatted_price": "$74,083",
      "formatted_change": "-1.05%",
      "updated_at": "2026-03-17T04:48:35.259071+00:00"
    },
    "iron": {
      "name": "Iron Ore",
      "price": 60.89,
      "change": 1.89,
      "formatted_price": "$60.89",
      "formatted_change": "+1.89%",
      "updated_at": "2026-03-17T04:48:35.309509+00:00"
    },
    "copper": {
      "name": "Copper",
      "price": 5.83,
      "change": -0.03,
      "formatted_price": "$5.83",
      "formatted_change": "-0.03%",
      "updated_at": "2026-03-17T04:48:35.364756+00:00"
    }
  }
}